torch/_VF.py
torch/__config__.py
torch/__future__.py
torch/__init__.py
torch/_appdirs.py
torch/_classes.py
torch/_compile.py
torch/_custom_ops.py
torch/_deploy.py
torch/_guards.py
torch/_jit_internal.py
torch/_linalg_utils.py
torch/_lobpcg.py
torch/_lowrank.py
torch/_meta_registrations.py
torch/_namedtensor_internals.py
torch/_ops.py
torch/_python_dispatcher.py
torch/_sources.py
torch/_storage_docs.py
torch/_tensor.py
torch/_tensor_docs.py
torch/_tensor_str.py
torch/_torch_docs.py
torch/_utils.py
torch/_utils_internal.py
torch/_vmap_internals.py
torch/_weights_only_unpickler.py
torch/functional.py
torch/hub.py
torch/library.py
torch/overrides.py
torch/quasirandom.py
torch/random.py
torch/return_types.py
torch/serialization.py
torch/storage.py
torch/torch_version.py
torch/types.py
torch/_awaits/__init__.py
torch/_custom_op/__init__.py
torch/_custom_op/autograd.py
torch/_custom_op/functional.py
torch/_custom_op/impl.py
torch/_decomp/__init__.py
torch/_decomp/decompositions.py
torch/_decomp/decompositions_for_jvp.py
torch/_decomp/decompositions_for_rng.py
torch/_dispatch/__init__.py
torch/_dispatch/python.py
torch/_dynamo/__init__.py
torch/_dynamo/allowed_functions.py
torch/_dynamo/bytecode_analysis.py
torch/_dynamo/bytecode_transformation.py
torch/_dynamo/cache_size.py
torch/_dynamo/codegen.py
torch/_dynamo/compiled_autograd.py
torch/_dynamo/comptime.py
torch/_dynamo/config.py
torch/_dynamo/config_utils.py
torch/_dynamo/convert_frame.py
torch/_dynamo/current_scope_id.py
torch/_dynamo/debug_utils.py
torch/_dynamo/decorators.py
torch/_dynamo/eval_frame.py
torch/_dynamo/exc.py
torch/_dynamo/external_utils.py
torch/_dynamo/guards.py
torch/_dynamo/hooks.py
torch/_dynamo/logging.py
torch/_dynamo/mutation_guard.py
torch/_dynamo/output_graph.py
torch/_dynamo/profiler.py
torch/_dynamo/replay_record.py
torch/_dynamo/resume_execution.py
torch/_dynamo/side_effects.py
torch/_dynamo/skipfiles.py
torch/_dynamo/source.py
torch/_dynamo/symbolic_convert.py
torch/_dynamo/test_case.py
torch_build_optim-0.1.1.dist-info/METADATA
torch_build_optim-0.1.1.dist-info/WHEEL
torch_build_optim-0.1.1.dist-info/top_level.txt
torch_build_optim-0.1.1.dist-info/RECORD
